{
  "_randomherb_avg": 0,
  "adamant_arrow": 48,
  "adamant_dart": 39,
  "adamant_full_helm": 2112,
  "adamant_kiteshield": 3264,
  "adamant_knife": 39,
  "adamant_platelegs": 3840,
  "adamantite_bar": 384,
  "adamantite_ore": 240,
  "airrune": 2,
  "antifire_potion": 158,
  "ashes": 1,
  "bass": 72,
  "big_bones": 0,
  "black_dart": 10,
  "black_knife": 11,
  "bloodrune": 30,
  "bodyrune": 1,
  "bones": 0,
  "bronze_arrow": 0,
  "bronze_dart": 0,
  "bronze_knife": 0,
  "chaosrune": 9,
  "coal": 27,
  "cosmicrune": 9,
  "cow_hide": 0,
  "deathrune": 18,
  "dragon_bones": 0,
  "dragon_longsword": 60000,
  "dragon_spear": 37440,
  "dragonhide_black": 48,
  "dragonhide_blue": 24,
  "dragonhide_green": 12,
  "dragonhide_red": 36,
  "dragonstone": 6000,
  "earthrune": 2,
  "eye_of_newt": 1,
  "feather": 1,
  "fire_battlestaff": 9300,
  "firerune": 2,
  "gold_bar": 180,
  "gold_ore": 90,
  "granite_shield": 33600,
  "guam_leaf": 1,
  "herb_avantoe": 28,
  "herb_cadantine": 39,
  "herb_dwarf_weed": 42,
  "herb_guam": 1,
  "herb_harralander": 12,
  "herb_irit": 24,
  "herb_kwuarm": 32,
  "herb_lantadyme": 40,
  "herb_marrentill": 3,
  "herb_ranarr": 15,
  "herb_tarromin": 6,
  "iron_arrow": 1,
  "iron_bar": 16,
  "iron_dart": 1,
  "iron_knife": 1,
  "iron_ore": 10,
  "lawrune": 24,
  "limpwurt_root": 4,
  "lobster": 90,
  "loop_half_key": 0,
  "magic_potion": 150,
  "magic_staff": 900,
  "marentill": 3,
  "mindrune": 1,
  "mithril_arrow": 19,
  "mithril_bar": 180,
  "mithril_chainbody": 1170,
  "mithril_dart": 15,
  "mithril_kiteshield": 1326,
  "mithril_knife": 16,
  "mithril_ore": 97,
  "mithril_sq_shield": 936,
  "naturerune": 12,
  "prayer_potion": 91,
  "ranging_potion": 172,
  "restore_potion": 52,
  "rune_2h": 38400,
  "rune_arrow": 240,
  "rune_battleaxe": 24960,
  "rune_chainbody": 30000,
  "rune_dagger": 4800,
  "rune_dart": 210,
  "rune_full_helm": 21120,
  "rune_kiteshield": 32640,
  "rune_knife": 100,
  "rune_longsword": 19200,
  "rune_med_helm": 11520,
  "rune_platebody": 39000,
  "rune_platelegs": 38400,
  "rune_scimitar": 15360,
  "rune_sq_shield": 23040,
  "shark": 180,
  "silver_ore": 45,
  "snape_grass": 6,
  "steel_arrow": 7,
  "steel_bar": 60,
  "steel_dart": 6,
  "steel_knife": 6,
  "super_attack": 108,
  "super_defence": 158,
  "super_strength": 132,
  "swordfish": 120,
  "tooth_half_key": 0,
  "tuna": 60,
  "uncut_diamond": 120,
  "uncut_emerald": 30,
  "uncut_ruby": 60,
  "uncut_sapphire": 15,
  "unicorn_horn_dust": 12,
  "unidentified_guam": 0,
  "vial_water": 1,
  "water_talisman": 2,
  "waterrune": 2,
  "weapon_poison": 86,
  "white_berries": 6
}